erebo/__init__.py
erebo/main.py
erebo/update_country_iso_redis.py
erebo/config/countries.json
erebo/config/enviroment.json
erebo/controllers/__init__.py
erebo/controllers/check_vpn.py
erebo/controllers/controller.py
erebo/controllers/daemon.py
erebo/controllers/daemon_io.py
erebo/controllers/restart_vpn.py
erebo/controllers/routes.py
erebo/controllers/up_container.py
erebo/core/__init__.py
erebo/core/docker_project.py
erebo/core/utils.py
erebo/core/vpn_utils.py
erebo/dispachers/__init__.py
erebo/dispachers/dispacher.py
erebo/model/__init__.py
erebo/model/rediss.py
erebo/settings/__init__.py
erebo/settings/errors.py
erebo/settings/settings.py
erebo-1.1.23.dist-info/DESCRIPTION.rst
erebo-1.1.23.dist-info/METADATA
erebo-1.1.23.dist-info/RECORD
erebo-1.1.23.dist-info/WHEEL
erebo-1.1.23.dist-info/entry_points.txt
erebo-1.1.23.dist-info/metadata.json
erebo-1.1.23.dist-info/top_level.txt
